notebooks/__init__.py
workflows/__init__.py
workflows/buckets.py
workflows/env.py
workflows/sql_dbs.py
workspace/__init__.py
workspace/config.py
workspace/settings.py
awsdp-0.1.0.dist-info/METADATA
awsdp-0.1.0.dist-info/WHEEL
awsdp-0.1.0.dist-info/top_level.txt
awsdp-0.1.0.dist-info/RECORD
