Metadata-Version: 2.1
Name: awsdp
Version: 0.1.0
Author-email: Phidata Team <awsdp@phidata.com>
Requires-Python: >3.7
Requires-Dist: awswrangler
Requires-Dist: boto3
Requires-Dist: duckdb
Requires-Dist: ipython
Requires-Dist: pandas
Requires-Dist: papermill
Requires-Dist: phidata (>=0.2.15)
Requires-Dist: pyarrow
Requires-Dist: requests
Requires-Dist: sqlalchemy
Requires-Dist: tiingo
Provides-Extra: dev
Requires-Dist: black[jupyter] ; extra == 'dev'
Requires-Dist: mypy ; extra == 'dev'
Requires-Dist: pytest ; extra == 'dev'
Requires-Dist: psycopg2-binary ; extra == 'dev'
Requires-Dist: types-requests ; extra == 'dev'
